{
  "version": "1.1.1",
  "windows": {
    "main": {
      "main": true,
      "url": "app://editor/index.html",
      "windowType": "dockable",
      "x": 2099,
      "y": 137,
      "width": 1280,
      "height": 781,
      "layout": {
        "children": [
          {
            "children": [
              {
                "active": 0,
                "children": [
                  "hierarchy"
                ],
                "height": 229,
                "type": "panel",
                "width": 304
              },
              {
                "active": 0,
                "children": [
                  "assets",
                  "cloud-function"
                ],
                "height": 430.984375,
                "type": "panel",
                "width": 304
              }
            ],
            "height": 663,
            "type": "dock-v",
            "width": 304
          },
          {
            "children": [
              {
                "active": 0,
                "children": [
                  "scene"
                ],
                "height": 329,
                "type": "panel",
                "width": 650
              },
              {
                "active": 0,
                "children": [
                  "console",
                  "timeline",
                  "game-window"
                ],
                "height": 331,
                "type": "panel",
                "width": 650
              }
            ],
            "height": 663,
            "type": "dock-v",
            "width": 650
          },
          {
            "active": 0,
            "children": [
              "inspector",
              "cocos-services"
            ],
            "height": 663,
            "type": "panel",
            "width": 304
          }
        ],
        "type": "dock-h"
      },
      "panels": [
        "hierarchy",
        "assets",
        "cloud-function",
        "scene",
        "console",
        "timeline",
        "game-window",
        "inspector",
        "cocos-services"
      ]
    },
    "worker": {},
    "window-1620266659569": {}
  },
  "panels": {
    "builder": {
      "x": 153,
      "y": 203,
      "width": 516,
      "height": 739
    }
  },
  "panelLabelWidth": {
    "builder": null
  }
}
